image/__init__.py
image_oc-1.0.1.dist-info/METADATA
image_oc-1.0.1.dist-info/WHEEL
image_oc-1.0.1.dist-info/licenses/LICENSE
image_oc-1.0.1.dist-info/RECORD
